jupyter_utils/__init__.py
jupyter_utils/conda.py
jupyter_utils/jupyter_utils.py
jupyter_utils/spark.py
jupyter_utils/tests/__init__.py
jupyter_utils/tests/test_jupyter_utils.py
jupyter_utils-1.2.6.dist-info/top_level.txt
jupyter_utils-1.2.6.dist-info/pbr.json
jupyter_utils-1.2.6.dist-info/METADATA
jupyter_utils-1.2.6.dist-info/DESCRIPTION.rst
jupyter_utils-1.2.6.dist-info/metadata.json
jupyter_utils-1.2.6.dist-info/WHEEL
jupyter_utils-1.2.6.dist-info/RECORD
